resilient_requester/__init__.py
resilient_requester/resilient_requester.py
resilient_requester/helpers/helper_functions.py
resilient_requester-0.1.3.dist-info/licenses/LICENSE
resilient_requester-0.1.3.dist-info/METADATA
resilient_requester-0.1.3.dist-info/WHEEL
resilient_requester-0.1.3.dist-info/top_level.txt
resilient_requester-0.1.3.dist-info/RECORD
