Metadata-Version: 2.4
Name: resilient-requester
Version: 0.1.3
Summary: A simple HTTP requester with retry and proxy support
Author-email: Chima Ihueze <chimaihueze@outlook.com>
License-Expression: MIT
Project-URL: Homepage, https://github.com/chimaihueze/resilient-requester
Project-URL: Repository, https://github.com/chimaihueze/resilient-requester
Project-URL: Issues, https://github.com/chimaihueze/resilient-requester/issues
Classifier: Development Status :: 3 - Alpha
Classifier: Intended Audience :: Developers
Classifier: Programming Language :: Python :: 3
Classifier: Programming Language :: Python :: 3.9
Classifier: Topic :: Internet :: WWW/HTTP
Classifier: Topic :: Software Development :: Libraries :: Python Modules
Requires-Python: >=3.9
License-File: LICENSE
Requires-Dist: fake-useragent>=2.2.0
Requires-Dist: requests>=2.32.4
Dynamic: license-file
